all_shortcuts-0.7.data/scripts/get
all_shortcuts-0.7.data/scripts/go
all_shortcuts-0.7.data/scripts/send
shortcuts/Models.py
shortcuts/__init__.py
shortcuts/services/__init__.py
shortcuts/services/sftp.py
shortcuts/services/ssh.py
shortcuts/services/libs/__init__.py
shortcuts/services/libs/destroyPrivateKey.py
shortcuts/services/libs/getServer.py
shortcuts/services/libs/makePrivateKey.py
all_shortcuts-0.7.dist-info/LICENSE
all_shortcuts-0.7.dist-info/METADATA
all_shortcuts-0.7.dist-info/WHEEL
all_shortcuts-0.7.dist-info/top_level.txt
all_shortcuts-0.7.dist-info/RECORD
