Metadata-Version: 2.1
Name: all-shortcuts
Version: 0.7
Summary: a app that simplify our shape of write orders
Home-page: https://github.com/whohe/shortcuts
Author: Wilson Hernández Ortiz
Author-email: who@whooami.me
License: UNKNOWN
Platform: UNKNOWN
